tdis/__init__.py
tdis/__main__.py
tests/__init__.py
tdis-0.0.1.dist-info/METADATA
tdis-0.0.1.dist-info/WHEEL
tdis-0.0.1.dist-info/entry_points.txt
tdis-0.0.1.dist-info/top_level.txt
tdis-0.0.1.dist-info/RECORD
